ml4t/diagnostic/AGENT.md
ml4t/diagnostic/__init__.py
ml4t/diagnostic/py.typed
ml4t/diagnostic/backends/__init__.py
ml4t/diagnostic/backends/adapter.py
ml4t/diagnostic/backends/polars_backend.py
ml4t/diagnostic/caching/__init__.py
ml4t/diagnostic/caching/cache.py
ml4t/diagnostic/caching/decorators.py
ml4t/diagnostic/caching/smart_cache.py
ml4t/diagnostic/config/AGENT.md
ml4t/diagnostic/config/README.md
ml4t/diagnostic/config/__init__.py
ml4t/diagnostic/config/barrier_config.py
ml4t/diagnostic/config/base.py
ml4t/diagnostic/config/event_config.py
ml4t/diagnostic/config/feature_config.py
ml4t/diagnostic/config/multi_signal_config.py
ml4t/diagnostic/config/portfolio_config.py
ml4t/diagnostic/config/report_config.py
ml4t/diagnostic/config/sharpe_config.py
ml4t/diagnostic/config/signal_config.py
ml4t/diagnostic/config/trade_analysis_config.py
ml4t/diagnostic/config/validation.py
ml4t/diagnostic/core/__init__.py
ml4t/diagnostic/core/numba_utils.py
ml4t/diagnostic/core/purging.py
ml4t/diagnostic/core/sampling.py
ml4t/diagnostic/errors/__init__.py
ml4t/diagnostic/evaluation/AGENT.md
ml4t/diagnostic/evaluation/__init__.py
ml4t/diagnostic/evaluation/autocorrelation.py
ml4t/diagnostic/evaluation/barrier_analysis.py
ml4t/diagnostic/evaluation/binary_metrics.py
ml4t/diagnostic/evaluation/dashboard.py
ml4t/diagnostic/evaluation/diagnostic_plots.py
ml4t/diagnostic/evaluation/event_analysis.py
ml4t/diagnostic/evaluation/excursion.py
ml4t/diagnostic/evaluation/feature_diagnostics.py
ml4t/diagnostic/evaluation/feature_outcome.py
ml4t/diagnostic/evaluation/framework.py
ml4t/diagnostic/evaluation/metric_registry.py
ml4t/diagnostic/evaluation/multi_signal.py
ml4t/diagnostic/evaluation/report_generation.py
ml4t/diagnostic/evaluation/signal_selector.py
ml4t/diagnostic/evaluation/stat_registry.py
ml4t/diagnostic/evaluation/themes.py
ml4t/diagnostic/evaluation/threshold_analysis.py
ml4t/diagnostic/evaluation/trade_analysis.py
ml4t/diagnostic/evaluation/trade_shap_dashboard.py
ml4t_diagnostic-0.1.0a1.dist-info/METADATA
ml4t_diagnostic-0.1.0a1.dist-info/WHEEL
ml4t_diagnostic-0.1.0a1.dist-info/licenses/LICENSE
ml4t_diagnostic-0.1.0a1.dist-info/RECORD
