Metadata-Version: 2.4
Name: ml4t-diagnostic
Version: 0.1.0a1
Summary: Comprehensive diagnostic and evaluation framework for quantitative finance ML workflows
Project-URL: Homepage, https://github.com/ml4t/ml4t-evaluation
Project-URL: Documentation, https://ml4t-evaluation.readthedocs.io
Project-URL: Repository, https://github.com/ml4t/ml4t-evaluation
Project-URL: Issues, https://github.com/ml4t/ml4t-evaluation/issues
Project-URL: Changelog, https://github.com/ml4t/ml4t-evaluation/blob/main/CHANGELOG.md
Author-email: QuantLab Team <info@quantlab.io>
Maintainer-email: QuantLab Contributors <dev@quantlab.io>
License: MIT
License-File: LICENSE
Keywords: backtesting,cross-validation,embargo,finance,machine-learning,polars,purging,quantitative-finance,statistical-tests,trading,validation
Classifier: Development Status :: 4 - Beta
Classifier: Intended Audience :: Developers
Classifier: Intended Audience :: Financial and Insurance Industry
Classifier: Intended Audience :: Science/Research
Classifier: License :: OSI Approved :: MIT License
Classifier: Operating System :: OS Independent
Classifier: Programming Language :: Python :: 3
Classifier: Programming Language :: Python :: 3.11
Classifier: Programming Language :: Python :: 3.12
Classifier: Programming Language :: Python :: 3.13
Classifier: Topic :: Office/Business :: Financial :: Investment
Classifier: Topic :: Scientific/Engineering :: Information Analysis
Classifier: Topic :: Scientific/Engineering :: Mathematics
Classifier: Typing :: Typed
Requires-Python: >=3.11
Requires-Dist: anywidget>=0.9.21
Requires-Dist: arch>=7.2.0
Requires-Dist: jinja2>=3.1.0
Requires-Dist: lightgbm>=4.6.0
Requires-Dist: numba>=0.57.0
Requires-Dist: numpy>=1.24.0
Requires-Dist: pandas-datareader>=0.10.0
Requires-Dist: pandas-market-calendars>=4.0.0
Requires-Dist: pandas>=2.0.0
Requires-Dist: plotly>=5.15.0
Requires-Dist: polars>=0.20.0
Requires-Dist: pyarrow>=14.0.0
Requires-Dist: pydantic>=2.0.0
Requires-Dist: pyyaml>=6.0
Requires-Dist: riskfolio-lib>=7.1.0
Requires-Dist: scikit-learn>=1.3.0
Requires-Dist: scipy>=1.10.0
Requires-Dist: setuptools>=80.9.0
Requires-Dist: statsmodels>=0.14.0
Requires-Dist: structlog>=23.0.0
Requires-Dist: sympy>=1.14.0
Requires-Dist: tabulate>=0.9.0
Requires-Dist: vectorbt>=0.28.2
Requires-Dist: xgboost>=2.1.4
Provides-Extra: advanced
Requires-Dist: arch>=6.0.0; extra == 'advanced'
Provides-Extra: all
Requires-Dist: arch>=6.0.0; extra == 'all'
Requires-Dist: hypothesis>=6.80.0; extra == 'all'
Requires-Dist: ipdb>=0.13.0; extra == 'all'
Requires-Dist: ipython>=8.14.0; extra == 'all'
Requires-Dist: kaleido>=0.2.0; extra == 'all'
Requires-Dist: lightgbm>=4.0.0; extra == 'all'
Requires-Dist: matplotlib>=3.7.0; extra == 'all'
Requires-Dist: myst-parser>=2.0.0; extra == 'all'
Requires-Dist: nbsphinx>=0.9.0; extra == 'all'
Requires-Dist: plotly>=5.15.0; extra == 'all'
Requires-Dist: pre-commit>=3.3.0; extra == 'all'
Requires-Dist: pypdf>=5.0.0; extra == 'all'
Requires-Dist: pytest-benchmark>=4.0.0; extra == 'all'
Requires-Dist: pytest-cov>=4.1.0; extra == 'all'
Requires-Dist: pytest-timeout>=2.1.0; extra == 'all'
Requires-Dist: pytest-xdist>=3.3.0; extra == 'all'
Requires-Dist: pytest>=7.4.0; extra == 'all'
Requires-Dist: ruff>=0.1.0; extra == 'all'
Requires-Dist: seaborn>=0.12.0; extra == 'all'
Requires-Dist: shap<0.50.0,>=0.41.0; extra == 'all'
Requires-Dist: sphinx-autodoc-typehints>=1.24.0; extra == 'all'
Requires-Dist: sphinx-rtd-theme>=1.3.0; extra == 'all'
Requires-Dist: sphinx>=7.0.0; extra == 'all'
Requires-Dist: streamlit>=1.28.0; extra == 'all'
Requires-Dist: ty; extra == 'all'
Requires-Dist: xgboost>=2.0.0; extra == 'all'
Provides-Extra: all-ml
Requires-Dist: cupy-cuda11x>=11.0.0; extra == 'all-ml'
Requires-Dist: lightgbm>=4.0.0; extra == 'all-ml'
Requires-Dist: shap<0.50.0,>=0.41.0; extra == 'all-ml'
Requires-Dist: tensorflow>=2.0.0; extra == 'all-ml'
Requires-Dist: xgboost>=2.0.0; extra == 'all-ml'
Provides-Extra: dashboard
Requires-Dist: streamlit>=1.28.0; extra == 'dashboard'
Provides-Extra: deep
Requires-Dist: shap<0.50.0,>=0.41.0; extra == 'deep'
Requires-Dist: tensorflow>=2.0.0; extra == 'deep'
Provides-Extra: dev
Requires-Dist: hypothesis>=6.80.0; extra == 'dev'
Requires-Dist: ipdb>=0.13.0; extra == 'dev'
Requires-Dist: ipython>=8.14.0; extra == 'dev'
Requires-Dist: pre-commit>=3.3.0; extra == 'dev'
Requires-Dist: pytest-benchmark>=4.0.0; extra == 'dev'
Requires-Dist: pytest-cov>=4.1.0; extra == 'dev'
Requires-Dist: pytest-timeout>=2.1.0; extra == 'dev'
Requires-Dist: pytest-xdist>=3.3.0; extra == 'dev'
Requires-Dist: pytest>=7.4.0; extra == 'dev'
Requires-Dist: ruff>=0.1.0; extra == 'dev'
Requires-Dist: ty; extra == 'dev'
Provides-Extra: docs
Requires-Dist: mkdocs-gen-files>=0.5.0; extra == 'docs'
Requires-Dist: mkdocs-literate-nav>=0.6.0; extra == 'docs'
Requires-Dist: mkdocs-material>=9.5.0; extra == 'docs'
Requires-Dist: mkdocs>=1.5.0; extra == 'docs'
Requires-Dist: mkdocstrings[python]>=0.24.0; extra == 'docs'
Provides-Extra: gpu
Requires-Dist: cupy-cuda11x>=11.0.0; extra == 'gpu'
Provides-Extra: integration
Provides-Extra: ml
Requires-Dist: lightgbm>=4.0.0; extra == 'ml'
Requires-Dist: shap<0.50.0,>=0.41.0; extra == 'ml'
Requires-Dist: xgboost>=2.0.0; extra == 'ml'
Provides-Extra: viz
Requires-Dist: kaleido>=0.2.0; extra == 'viz'
Requires-Dist: matplotlib>=3.7.0; extra == 'viz'
Requires-Dist: plotly>=5.15.0; extra == 'viz'
Requires-Dist: pypdf>=5.0.0; extra == 'viz'
Requires-Dist: seaborn>=0.12.0; extra == 'viz'
